Workbook
Name employees: Sheet3!$A$1:$J$22

Sheet Sheet2
A1: sno | B1: name | C1: marks | D1: Result | E1: Grade
A2: 1 | B2: Anil | C2: 25 | D2: =IF(C2>34,"Pass","Fail") -> Fail | E2: =IF(C2>90,"A+",IF(C2>80,"A",IF(C2>70,"B+",IF(C2>60,"B",IF(C2>50,"C+",IF(C2>34,"C","F")))))) -> F
A3: 2 | B3: Arun | C3: 45 | D3: =IF(C3>34,"Pass","Fail") -> Pass | E3: =IF(C3>90,"A+",IF(C3>80,"A",IF(C3>70,"B+",IF(C3>60,"B",IF(C3>50,"C+",IF(C3>34,"C","F")))))) -> C | H3: 90+ | I3: A+
A4: 3 | B4: Sunday | C4: 25 | D4: =IF(C4>34,"Pass","Fail") -> Fail | E4: =IF(C4>90,"A+",IF(C4>80,"A",IF(C4>70,"B+",IF(C4>60,"B",IF(C4>50,"C+",IF(C4>34,"C","F")))))) -> F | H4: 80+ | I4: A
A5: 4 | B5: Olivia | C5: 85 | D5: =IF(C5>34,"Pass","Fail") -> Pass | E5: =IF(C5>90,"A+",IF(C5>80,"A",IF(C5>70,"B+",IF(C5>60,"B",IF(C5>50,"C+",IF(C5>34,"C","F")))))) -> A | H5: 70+ | I5: B+
A6: 5 | B6: Alex | C6: 75 | D6: =IF(C6>34,"Pass","Fail") -> Pass | E6: =IF(C6>90,"A+",IF(C6>80,"A",IF(C6>70,"B+",IF(C6>60,"B",IF(C6>50,"C+",IF(C6>34,"C","F")))))) -> B+ | H6: 60+ | I6: B
A7: 6 | B7: Oxana | C7: 94 | D7: =IF(C7>34,"Pass","Fail") -> Pass | E7: =IF(C7>90,"A+",IF(C7>80,"A",IF(C7>70,"B+",IF(C7>60,"B",IF(C7>50,"C+",IF(C7>34,"C","F")))))) -> A+ | H7: 50+ | I7: c+
A8: 7 | B8: John | C8: 24 | D8: =IF(C8>34,"Pass","Fail") -> Fail | E8: =IF(C8>90,"A+",IF(C8>80,"A",IF(C8>70,"B+",IF(C8>60,"B",IF(C8>50,"C+",IF(C8>34,"C","F")))))) -> F | H8: 34+ | I8: C
A9: 8 | B9: Ron | C9: 85 | D9: =IF(C9>34,"Pass","Fail") -> Pass | E9: =IF(C9>90,"A+",IF(C9>80,"A",IF(C9>70,"B+",IF(C9>60,"B",IF(C9>50,"C+",IF(C9>34,"C","F")))))) -> A | I9: f

Sheet Sheet3
A1: EmpID | B1: Name | C1: Email | D1: Department | E1: Salary | F1: Exp | G1: Rating | H1: bonus(20% ro 3+ rating else 10%) | I1: pf(7%) | J1: Net salary
A2: 101 | B2: Amit Sharma | C2: amit.sharma@gmail.com | D2: IT | E2: 55000 | F2: 2 | G2: 4 | H2: =IF(G2>3,E2*20%,E2*10%) -> 11000 | I2: =E2*7% -> 3850 | J2: =E2+H2-I2 -> 62150
A3: 102 | B3: Neha Patel | C3: neha.patel@gmail.com | D3: HR | E3: 48000 | F3: 3 | G3: 4 | H3: =IF(G3>3,E3*20%,E3*10%) -> 9600 | I3: =E3*7% -> 3360 | J3: =E3+H3-I3 -> 54240
A4: 103 | B4: Raj Verma | C4: raj.verma@gmail.com | D4: IT | E4: 72000 | F4: 5 | G4: 5 | H4: =IF(G4>3,E4*20%,E4*10%) -> 14400 | I4: =E4*7% -> 5040 | J4: =E4+H4-I4 -> 81360
A5: 104 | B5: Priya Singh | C5: priya.singh@gmail.com | D5: Finance | E5: 65000 | F5: 4 | G5: 4 | H5: =IF(G5>3,E5*20%,E5*10%) -> 13000 | I5: =E5*7% -> 4550 | J5: =E5+H5-I5 -> 73450
A6: 105 | B6: Rohit Mehta | C6: rohit.mehta@gmail.com | D6: Sales | E6: 45000 | F6: 2 | G6: 3 | H6: =IF(G6>3,E6*20%,E6*10%) -> 4500 | I6: =E6*7% -> 3150 | J6: =E6+H6-I6 -> 46350
A7: 106 | B7: Anjali Shah | C7: anjali.shah@gmail.com | D7: IT | E7: 68000 | F7: 4 | G7: 4 | H7: =IF(G7>3,E7*20%,E7*10%) -> 13600 | I7: =E7*7% -> 4760 | J7: =E7+H7-I7 -> 76840
A8: 107 | B8: Vikas Gupta | C8: vikas.gupta@gmail.com | D8: HR | E8: 52000 | F8: 5 | G8: 5 | H8: =IF(G8>3,E8*20%,E8*10%) -> 10400 | I8: =E8*7% -> 3640 | J8: =E8+H8-I8 -> 58760
A9: 108 | B9: Pooja Joshi | C9: pooja.joshi@gmail.com | D9: Sales | E9: 58000 | F9: 3 | G9: 4 | H9: =IF(G9>3,E9*20%,E9*10%) -> 11600 | I9: =E9*7% -> 4060 | J9: =E9+H9-I9 -> 65540
A10: 109 | B10: Karan Desai | C10: karan.desai@gmail.com | D10: Finance | E10: 75000 | F10: 6 | G10: 5 | H10: =IF(G10>3,E10*20%,E10*10%) -> 15000 | I10: =E10*7% -> 5250 | J10: =E10+H10-I10 -> 84750
A11: 110 | B11: Riya Kapoor | C11: riya.kapoor@gmail.com | D11: IT | E11: 61000 | F11: 3 | G11: 3 | H11: =IF(G11>3,E11*20%,E11*10%) -> 6100 | I11: =E11*7% -> 4270 | J11: =E11+H11-I11 -> 62830
A12: 111 | B12: Suresh Yadav | C12: suresh.yadav@gmail.com | D12: Operations | E12: 50000 | F12: 4 | G12: 4 | H12: =IF(G12>3,E12*20%,E12*10%) -> 10000 | I12: =E12*7% -> 3500 | J12: =E12+H12-I12 -> 56500
A13: 112 | B13: Kavita Rao | C13: kavita.rao@gmail.com | D13: HR | E13: 62000 | F13: 6 | G13: 5 | H13: =IF(G13>3,E13*20%,E13*10%) -> 12400 | I13: =E13*7% -> 4340 | J13: =E13+H13-I13 -> 70060
... A22: 121 | B22: Anil | C22: anil@sldfj | D22: IT | E22: 54255 | F22: 6 | G22: 2 | H22: =IF(G22>3,E22*20%,E22*10%) -> 5425.5 | I22: =E22*7% -> 3797.85 | J22: =E22+H22-I22 -> 55882.65

Sheet Sheet4
A1: Row Labels | B1: No of Emps | C1: max salary | D1: Sum of Salary | F1: Row Labels | G1: Count of EmpID
A2: Finance | B2: 4 | C2: 75000 | D2: 263000 | F2: 2 | G2: 1
A3: HR | B3: 4 | C3: 62000 | D3: 208000 | F3: 3 | G3: 5
A4: IT | B4: 7 | C4: 85000 | D4: 471255 | F4: 4 | G4: 8
A5: Operations | B5: 2 | C5: 57000 | D5: 107000 | F5: 5 | G5: 7
A6: Sales | B6: 4 | C6: 70000 | D6: 222000 | F6: Grand Total | G6: 21
A7: Grand Total | B7: 21 | C7: 85000 | D7: 1271255

Sheet Sheet1
C1: rating >3 | D1: rating<=3 | E1: salary>60k | F1: salary<60k | G1: yrs of exp <2 | H1: yrs of exp>2
A2: Total Emps | B2: =COUNT(Sheet3!A:A) -> 21 | C2: =COUNTIF(Sheet3!G:G,">3") -> 15
A3: IT | B3: =COUNTIF(Sheet3!D:D,A3) -> 7 | C3: =COUNTIFS(Sheet3!D:D,A3,Sheet3!G:G,">3") -> 5
A4: HR | B4: =COUNTIF(Sheet3!D:D,A4) -> 4 | C4: =COUNTIFS(Sheet3!D:D,A4,Sheet3!G:G,">3") -> 3
A5: Finance | B5: =COUNTIF(Sheet3!D:D,A5) -> 4 | C5: =COUNTIFS(Sheet3!D:D,A5,Sheet3!G:G,">3") -> 3
A6: Sales | B6: =COUNTIF(Sheet3!D:D,A6) -> 4 | C6: =COUNTIFS(Sheet3!D:D,A6,Sheet3!G:G,">3") -> 2
A7: Operations | B7: =COUNTIF(Sheet3!D:D,A7) -> 2 | C7: =COUNTIFS(Sheet3!D:D,A7,Sheet3!G:G,">3") -> 2

Sheet Sheet5
A1: OrderID | B1: Date | C1: Salesperson | D1: Region | E1: Product | F1: Category | G1: CustomerType | H1: Quantity | I1: UnitPrice | J1: Discount | K1: PaymentMethod | L1: net price | M1: TotalSales
A2: 1001 | B2: 45662 | C2: Amit | D2: North | E2: Laptop | F2: Electronics | G2: Retail | H2: 2 | I2: 55000 | J2: 0.05 | K2: Credit Card | L2: =I2- (I2*J2) -> 52250 | M2: =L2*H2 -> 104500
A3: 1002 | B3: 45664 | C3: Neha | D3: South | E3: Mobile | F3: Electronics | G3: Wholesale | H3: 5 | I3: 22000 | J3: 0.1 | K3: UPI | L3: =I3- (I3*J3) -> 19800 | M3: =L3*H3 -> 99000
A4: 1003 | B4: 45667 | C4: Raj | D4: East | E4: Keyboard | F4: Accessories | G4: Retail | H4: 8 | I4: 1200 | J4: 0 | K4: Cash | L4: =I4- (I4*J4) -> 1200 | M4: =L4*H4 -> 9600
A5: 1004 | B5: 45669 | C5: Priya | D5: West | E5: Monitor | F5: Electronics | G5: Retail | H5: 3 | I5: 15000 | J5: 0.05 | K5: Credit Card | L5: =I5- (I5*J5) -> 14250 | M5: =L5*H5 -> 42750
A6: 1005 | B6: 45672 | C6: Amit | D6: North | E6: Mouse | F6: Accessories | G6: Wholesale | H6: 10 | I6: 800 | J6: 0.1 | K6: UPI | L6: =I6- (I6*J6) -> 720 | M6: =L6*H6 -> 7200
A7: 1006 | B7: 45675 | C7: Neha | D7: South | E7: Laptop | F7: Electronics | G7: Retail | H7: 1 | I7: 55000 | J7: 0.05 | K7: Cash | L7: =I7- (I7*J7) -> 52250 | M7: =L7*H7 -> 52250
A8: 1007 | B8: 45678 | C8: Raj | D8: East | E8: Printer | F8: Electronics | G8: Wholesale | H8: 4 | I8: 18000 | J8: 0.08 | K8: Bank Transfer | L8: =I8- (I8*J8) -> 16560 | M8: =L8*H8 -> 66240
A9: 1008 | B9: 45682 | C9: Priya | D9: West | E9: Chair | F9: Furniture | G9: Retail | H9: 6 | I9: 6500 | J9: 0.05 | K9: Credit Card | L9: =I9- (I9*J9) -> 6175 | M9: =L9*H9 -> 37050
A10: 1009 | B10: 45685 | C10: Amit | D10: North | E10: Desk | F10: Furniture | G10: Wholesale | H10: 3 | I10: 12000 | J10: 0.1 | K10: UPI | L10: =I10- (I10*J10) -> 10800 | M10: =L10*H10 -> 32400
A11: 1010 | B11: 45687 | C11: Neha | D11: South | E11: Mobile | F11: Electronics | G11: Retail | H11: 4 | I11: 22000 | J11: 0.05 | K11: Cash | L11: =I11- (I11*J11) -> 20900 | M11: =L11*H11 -> 83600
A12: 1011 | B12: 45690 | C12: Raj | D12: East | E12: Laptop | F12: Electronics | G12: Wholesale | H12: 2 | I12: 55000 | J12: 0.12 | K12: Bank Transfer | L12: =I12- (I12*J12) -> 48400 | M12: =L12*H12 -> 96800
A13: 1012 | B13: 45693 | C13: Priya | D13: West | E13: Keyboard | F13: Accessories | G13: Retail | H13: 12 | I13: 1200 | J13: 0 | K13: UPI | L13: =I13- (I13*J13) -> 1200 | M13: =L13*H13 -> 14400
... A51: 1050 | B51: 45808 | C51: Neha | D51: South | E51: Printer | F51: Electronics | G51: Retail | H51: 3 | I51: 18000 | J51: 0.05 | K51: Credit Card | L51: =I51- (I51*J51) -> 17100 | M51: =L51*H51 -> 51300
